pyDMS/__init__.py
pyDMS/pyDMS.py
pyDMS/pyDMSUtils.py
python_dms-1.2.1.dist-info/METADATA
python_dms-1.2.1.dist-info/WHEEL
python_dms-1.2.1.dist-info/licenses/LICENSE
python_dms-1.2.1.dist-info/RECORD
