Metadata-Version: 2.4
Name: python-dms
Version: 1.2.1
Summary: Python implementation of Data Mining Sharpener (DMS)
Author-email: Radoslaw Guzinski <rmgu@dhigroup.com>
License: Copyright 2018 Radoslaw Guzinski and contributors listed in the README.md file.
License-File: LICENSE
Keywords: DMS,Remote Sensing,data mining sharpener,disaggregation,image sharpening
Classifier: Development Status :: 4 - Beta
Classifier: Intended Audience :: Science/Research
Classifier: License :: OSI Approved :: GNU General Public License (GPL)
Classifier: Programming Language :: Python :: 3
Classifier: Topic :: Scientific/Engineering
Requires-Python: >=3.9
Requires-Dist: numba
Requires-Dist: numpy>=1.10
Requires-Dist: pyproj>2.2.0
Requires-Dist: scikit-learn
Requires-Dist: scipy
Provides-Extra: dev
Requires-Dist: build; extra == 'dev'
Requires-Dist: ipykernel; extra == 'dev'
Requires-Dist: mkdocs; extra == 'dev'
Requires-Dist: mkdocs-material; extra == 'dev'
Requires-Dist: mkdocstrings[python]; extra == 'dev'
Requires-Dist: pytest; extra == 'dev'
Requires-Dist: ruff; extra == 'dev'
Provides-Extra: gdal
Requires-Dist: gdal>=3.0.0; extra == 'gdal'
Provides-Extra: test
Requires-Dist: pytest; extra == 'test'
